README.md
smartbindb/__init__.py
smartbindb/smartdb.py
smartbindb/data/smartbin.db
smartbindb-5.17.1.dist-info/METADATA
smartbindb-5.17.1.dist-info/WHEEL
smartbindb-5.17.1.dist-info/RECORD
