Metadata-Version: 2.4
Name: smartbindb
Version: 5.17.1
Summary: A powerful Asynchronous Python library for getting bins database by country name or bank name, also supports bin lookup, supporting bots, MTProto API frameworks, and Python scripts
Project-URL: Homepage, https://github.com/abirxdhack
Project-URL: Documentation, https://abirxdhack.github.io/SmartBinDBDocs/
Project-URL: Download, https://pypi.org/project/smartbindb/
Project-URL: PyPI, https://pypi.org/project/smartbindb/
Author-email: ISmartCoder <abirxdhackz.info.me@gmail.com>
License: Proprietary
Keywords: async,bank,bin,bot,country,database,lookup,mtproto,python-library,telegram-bot
Classifier: Development Status :: 5 - Production/Stable
Classifier: Framework :: AsyncIO
Classifier: Intended Audience :: Developers
Classifier: License :: Other/Proprietary License
Classifier: Operating System :: OS Independent
Classifier: Programming Language :: Python :: 3
Classifier: Programming Language :: Python :: 3 :: Only
Classifier: Programming Language :: Python :: 3.8
Classifier: Programming Language :: Python :: 3.9
Classifier: Programming Language :: Python :: 3.10
Classifier: Programming Language :: Python :: 3.11
Classifier: Programming Language :: Python :: 3.12
Classifier: Topic :: Database
Classifier: Topic :: Internet :: WWW/HTTP
Classifier: Topic :: Software Development :: Libraries
Classifier: Topic :: Software Development :: Libraries :: Python Modules
Requires-Python: >=3.8
Requires-Dist: asyncio
Requires-Dist: pycountry
Requires-Dist: pycountry-convert
